settlers/__init__.py
settlers/ascii_display.py
settlers-0.0.2.dist-info/LICENSE.txt
settlers-0.0.2.dist-info/METADATA
settlers-0.0.2.dist-info/WHEEL
settlers-0.0.2.dist-info/top_level.txt
settlers-0.0.2.dist-info/RECORD
