Metadata-Version: 2.1
Name: settlers
Version: 0.0.2
Summary: An ASCII display and backend logic package for Settlers of Catan
Author-email: Porter Nilsson <porter.nilsson@gmail.com>
Project-URL: Homepage, https://github.com/PorterNilsson/settlers
Classifier: Programming Language :: Python :: 3
Classifier: License :: OSI Approved :: MIT License
Classifier: Operating System :: OS Independent
Requires-Python: >=3.8
License-File: LICENSE.txt
